crystalipf/__init__.py
crystalipf/cubic.py
crystalipf-0.0.1.dist-info/LICENSE
crystalipf-0.0.1.dist-info/METADATA
crystalipf-0.0.1.dist-info/WHEEL
crystalipf-0.0.1.dist-info/top_level.txt
crystalipf-0.0.1.dist-info/RECORD
