Metadata-Version: 2.1
Name: crystalipf
Version: 0.0.1
Summary: Easy-to-use library for calculating the rgb values of the IPF map of cubic materials.
Author-email: Silvio Achilles <achilles.develop@proton.me>
Project-URL: Homepage, https://github.com/silvioachilles/crystalipf
Project-URL: Issues, https://github.com/silvioachilles/crystalipf/issues
Classifier: Programming Language :: Python :: 3
Classifier: License :: OSI Approved :: MIT License
Classifier: Operating System :: OS Independent
Requires-Python: >=3.9
License-File: LICENSE
Requires-Dist: numpy
Requires-Dist: matplotlib
